MANIFEST.in
README.md
setup.py
beautifier/__init__.py
beautifier.egg-info/PKG-INFO
beautifier.egg-info/SOURCES.txt
beautifier.egg-info/dependency_links.txt
beautifier.egg-info/not-zip-safe
beautifier.egg-info/top_level.txt
beautifier/helpers/free_domain_list.txt