Metadata-Version: 2.1
Name: beautifier
Version: 0.5.5
Summary: Cleanup and beautifier emails, urls and patterns
Home-page: https://github.com/labtocat/beautifier
Author: Sachin Philip Mathew
Author-email: me@imsach.in
License: MIT
Platform: UNKNOWN
Classifier: Development Status :: 5 - Production/Stable
Classifier: Programming Language :: Python :: 2.7
Classifier: Programming Language :: Python :: 3
Classifier: Intended Audience :: Developers
Classifier: Topic :: Software Development :: Libraries
Classifier: License :: OSI Approved :: MIT License
Classifier: Operating System :: OS Independent
